HoodHod/HoodHod.py
HoodHod/__init__.py
HoodHod-0.2.0.dist-info/METADATA
HoodHod-0.2.0.dist-info/WHEEL
HoodHod-0.2.0.dist-info/top_level.txt
HoodHod-0.2.0.dist-info/RECORD
