Metadata-Version: 2.1
Name: HoodHod
Version: 0.2.0
Summary: A package for performing simple linear regression and binary decision tree classification and visualize the tree.
Home-page: UNKNOWN
Author: Derradji Aicha Elbatoul
Author-email: derradjiaichaelbatoul@gmail.com
License: UNKNOWN
Platform: UNKNOWN
Classifier: Programming Language :: Python :: 3
Classifier: License :: OSI Approved :: MIT License
Classifier: Operating System :: OS Independent
Requires-Dist: graphviz
Requires-Dist: numpy
Requires-Dist: prettytable
